pyproject.toml
src/mcp_python_exec/__init__.py
src/mcp_python_exec/__main__.py
src/mcp_python_exec/executor.py
src/mcp_python_exec/mpl_backend.py
src/mcp_python_exec/server.py
src/mcp_python_exec/session.py
src/mcp_python_exec.egg-info/PKG-INFO
src/mcp_python_exec.egg-info/SOURCES.txt
src/mcp_python_exec.egg-info/dependency_links.txt
src/mcp_python_exec.egg-info/entry_points.txt
src/mcp_python_exec.egg-info/requires.txt
src/mcp_python_exec.egg-info/top_level.txt
src/pychroot/__init__.py
src/pychroot/base.py
src/pychroot/exceptions.py
src/pychroot/utils.py
src/pychroot/scripts/__init__.py
src/pychroot/scripts/pychroot.py