Metadata-Version: 2.4
Name: mcp-python-exec
Version: 0.1.0
Summary: MCP server to execute Python code in separate chroot environments
Requires-Python: >=3.11
Requires-Dist: snakeoil
Requires-Dist: mcp
Requires-Dist: pillow
Requires-Dist: trio
Requires-Dist: anycorn
Requires-Dist: uvloop
